karl/__init__.py
karl/v1.py
karl/v2.py
karl/v3.py
libkarl-0.4.5.dist-info/LICENSE.txt
libkarl-0.4.5.dist-info/METADATA
libkarl-0.4.5.dist-info/WHEEL
libkarl-0.4.5.dist-info/top_level.txt
libkarl-0.4.5.dist-info/RECORD
