Metadata-Version: 2.1
Name: libkarl
Version: 0.4.5
Summary: Eine Bibliothek für KARL, den kleinen autonomen Roboter für die Lehre
Home-page: UNKNOWN
License: UNKNOWN
Platform: UNKNOWN
Classifier: Programming Language :: Python :: Implementation :: MicroPython
License-File: LICENSE.txt
